yaqd_labjack/VERSION
yaqd_labjack/__init__.py
yaqd_labjack/__version__.py
yaqd_labjack/_bytes.py
yaqd_labjack/_io.py
yaqd_labjack/_labjack_analog_output.py
yaqd_labjack/_labjack_digital_output.py
yaqd_labjack/_labjack_sensor.py
yaqd_labjack/labjack-analog-output.avpr
yaqd_labjack/labjack-analog-output.toml
yaqd_labjack/labjack-digital-output.avpr
yaqd_labjack/labjack-digital-output.toml
yaqd_labjack/labjack-sensor.avpr
yaqd_labjack/labjack-sensor.toml
yaqd_labjack-2023.8.0.dist-info/entry_points.txt
yaqd_labjack-2023.8.0.dist-info/LICENSE
yaqd_labjack-2023.8.0.dist-info/WHEEL
yaqd_labjack-2023.8.0.dist-info/METADATA
yaqd_labjack-2023.8.0.dist-info/RECORD
